gg_fpga/__init__.py
gg_fpga/app.sv
gg_fpga/auto_run.py
gg_fpga/cme_md_parser.sv
gg_fpga/functions.sv
gg_fpga/gg_fpga.sv
gg_fpga/md_runner.py
gg_fpga/pcapfile.pcap
gg_fpga/pcapparser_10gbmac.sv
gg_fpga/run.py
gg_fpga/triggerer.sv
gg_fpga-0.0.19.dist-info/METADATA
gg_fpga-0.0.19.dist-info/WHEEL
gg_fpga-0.0.19.dist-info/licenses/LICENSE
gg_fpga-0.0.19.dist-info/RECORD
