Metadata-Version: 2.3
Name: gg_fpga
Version: 0.0.19
Summary: FPGA ultra low latency options triggering
Author: Chloe Grace Moretz
License-File: LICENSE
Classifier: License :: OSI Approved :: Mozilla Public License 2.0 (MPL 2.0)
Classifier: Operating System :: OS Independent
Classifier: Programming Language :: Python :: 3
Requires-Python: >=3.8
Requires-Dist: cocotb
Requires-Dist: matplotlib
Requires-Dist: numpy
Requires-Dist: xlwt
